{
  "spriteSheetName": "SPRITESHEET_CORE",
  "textureName": "TEXTURE_CORE",
  "spriteFrames": [
    {
      "name": "TEXTURE_GAMEPAD_DPAD_DARK",
      "x": 0,
      "y": 196,
      "w": 96,
      "h": 96,
      "pivotX": 0,
      "pivotY": 0,
      "scaleX": 1.0,
      "scaleY": 1.0,
      "anchorToPointName": null,
      "anchorPoints": []
    },
    {
      "name": "TEXTURE_GAMEPAD_DPAD_LIGHT",
      "x": 97,
      "y": 196,
      "w": 96,
      "h": 96,
      "pivotX": 0,
      "pivotY": 0,
      "scaleX": 1.0,
      "scaleY": 1.0,
      "anchorToPointName": null,
      "anchorPoints": []
    },
    {
      "name": "TEXTURE_GAMEPAD_LAYOUT_DARK_COLOR",
      "x": 194,
      "y": 196,
      "w": 96,
      "h": 96,
      "pivotX": 0,
      "pivotY": 0,
      "scaleX": 1.0,
      "scaleY": 1.0,
      "anchorToPointName": null,
      "anchorPoints": []
    },
    {
      "name": "TEXTURE_DESELECTED_LARGE",
      "x": 0,
      "y": 66,
      "w": 64,
      "h": 64,
      "pivotX": 0,
      "pivotY": 0,
      "scaleX": 1.0,
      "scaleY": 1.0,
      "anchorToPointName": null,
      "anchorPoints": []
    },
    {
      "name": "TEXTURE_DESELECTED_MEDIUM",
      "x": 65,
      "y": 66,
      "w": 64,
      "h": 64,
      "pivotX": 0,
      "pivotY": 0,
      "scaleX": 1.0,
      "scaleY": 1.0,
      "anchorToPointName": null,
      "anchorPoints": []
    },
    {
      "name": "TEXTURE_FOOTER_64X64",
      "x": 0,
      "y": 131,
      "w": 64,
      "h": 64,
      "pivotX": 0,
      "pivotY": 0,
      "scaleX": 1.0,
      "scaleY": 1.0,
      "anchorToPointName": null,
      "anchorPoints": []
    },
    {
      "name": "TEXTURE_FOOTER_END_64X64",
      "x": 65,
      "y": 131,
      "w": 64,
      "h": 64,
      "pivotX": 0,
      "pivotY": 0,
      "scaleX": 1.0,
      "scaleY": 1.0,
      "anchorToPointName": null,
      "anchorPoints": []
    },
    {
      "name": "TEXTURE_FOOTER_TRANSITION",
      "x": 130,
      "y": 131,
      "w": 64,
      "h": 64,
      "pivotX": 0,
      "pivotY": 0,
      "scaleX": 1.0,
      "scaleY": 1.0,
      "anchorToPointName": null,
      "anchorPoints": []
    },
    {
      "name": "TEXTURE_ICON_INFO",
      "x": 291,
      "y": 196,
      "w": 64,
      "h": 64,
      "pivotX": 0,
      "pivotY": 0,
      "scaleX": 1.0,
      "scaleY": 1.0,
      "anchorToPointName": null,
      "anchorPoints": []
    },
    {
      "name": "TEXTURE_ICON_WARNING",
      "x": 356,
      "y": 196,
      "w": 64,
      "h": 64,
      "pivotX": 0,
      "pivotY": 0,
      "scaleX": 1.0,
      "scaleY": 1.0,
      "anchorToPointName": null,
      "anchorPoints": []
    },
    {
      "name": "TEXTURE_OUTLINE_LARGE",
      "x": 0,
      "y": 293,
      "w": 64,
      "h": 64,
      "pivotX": 0,
      "pivotY": 0,
      "scaleX": 1.0,
      "scaleY": 1.0,
      "anchorToPointName": null,
      "anchorPoints": []
    },
    {
      "name": "TEXTURE_SELECTED_LARGE",
      "x": 0,
      "y": 391,
      "w": 64,
      "h": 64,
      "pivotX": 0,
      "pivotY": 0,
      "scaleX": 1.0,
      "scaleY": 1.0,
      "anchorToPointName": null,
      "anchorPoints": []
    },
    {
      "name": "TEXTURE_KEY_LARGE",
      "x": 606,
      "y": 131,
      "w": 96,
      "h": 32,
      "pivotX": 0,
      "pivotY": 0,
      "scaleX": 1.0,
      "scaleY": 1.0,
      "anchorToPointName": null,
      "anchorPoints": []
    },
    {
      "name": "TEXTURE_KEY_MEDIUM",
      "x": 703,
      "y": 131,
      "w": 64,
      "h": 32,
      "pivotX": 0,
      "pivotY": 0,
      "scaleX": 1.0,
      "scaleY": 1.0,
      "anchorToPointName": null,
      "anchorPoints": []
    },
    {
      "name": "TEXTURE_GAMEPAD_LB_DARK",
      "x": 493,
      "y": 66,
      "w": 48,
      "h": 32,
      "pivotX": 0,
      "pivotY": 0,
      "scaleX": 1.0,
      "scaleY": 1.0,
      "anchorToPointName": null,
      "anchorPoints": []
    },
    {
      "name": "TEXTURE_GAMEPAD_LB_LIGHT",
      "x": 542,
      "y": 66,
      "w": 48,
      "h": 32,
      "pivotX": 0,
      "pivotY": 0,
      "scaleX": 1.0,
      "scaleY": 1.0,
      "anchorToPointName": null,
      "anchorPoints": []
    },
    {
      "name": "TEXTURE_GAMEPAD_LT_DARK",
      "x": 657,
      "y": 66,
      "w": 48,
      "h": 32,
      "pivotX": 0,
      "pivotY": 0,
      "scaleX": 1.0,
      "scaleY": 1.0,
      "anchorToPointName": null,
      "anchorPoints": []
    },
    {
      "name": "TEXTURE_GAMEPAD_LT_LIGHT",
      "x": 706,
      "y": 66,
      "w": 48,
      "h": 32,
      "pivotX": 0,
      "pivotY": 0,
      "scaleX": 1.0,
      "scaleY": 1.0,
      "anchorToPointName": null,
      "anchorPoints": []
    },
    {
      "name": "TEXTURE_GAMEPAD_RB_DARK",
      "x": 821,
      "y": 66,
      "w": 48,
      "h": 32,
      "pivotX": 0,
      "pivotY": 0,
      "scaleX": 1.0,
      "scaleY": 1.0,
      "anchorToPointName": null,
      "anchorPoints": []
    },
    {
      "name": "TEXTURE_GAMEPAD_RB_LIGHT",
      "x": 870,
      "y": 66,
      "w": 48,
      "h": 32,
      "pivotX": 0,
      "pivotY": 0,
      "scaleX": 1.0,
      "scaleY": 1.0,
      "anchorToPointName": null,
      "anchorPoints": []
    },
    {
      "name": "TEXTURE_GAMEPAD_RT_DARK",
      "x": 195,
      "y": 131,
      "w": 48,
      "h": 32,
      "pivotX": 0,
      "pivotY": 0,
      "scaleX": 1.0,
      "scaleY": 1.0,
      "anchorToPointName": null,
      "anchorPoints": []
    },
    {
      "name": "TEXTURE_GAMEPAD_RT_LIGHT",
      "x": 244,
      "y": 131,
      "w": 48,
      "h": 32,
      "pivotX": 0,
      "pivotY": 0,
      "scaleX": 1.0,
      "scaleY": 1.0,
      "anchorToPointName": null,
      "anchorPoints": []
    },
    {
      "name": "TEXTURE_AUTOSCROLL",
      "x": 0,
      "y": 0,
      "w": 32,
      "h": 32,
      "pivotX": 0,
      "pivotY": 0,
      "scaleX": 1.0,
      "scaleY": 1.0,
      "anchorToPointName": null,
      "anchorPoints": []
    },
    {
      "name": "TEXTURE_CHECKBOX_CHECKED",
      "x": 0,
      "y": 33,
      "w": 32,
      "h": 32,
      "pivotX": 0,
      "pivotY": 0,
      "scaleX": 1.0,
      "scaleY": 1.0,
      "anchorToPointName": null,
      "anchorPoints": []
    },
    {
      "name": "TEXTURE_CHECKBOX_UNCHECKED",
      "x": 33,
      "y": 33,
      "w": 32,
      "h": 32,
      "pivotX": 0,
      "pivotY": 0,
      "scaleX": 1.0,
      "scaleY": 1.0,
      "anchorToPointName": null,
      "anchorPoints": []
    },
    {
      "name": "TEXTURE_COLLAPSE",
      "x": 66,
      "y": 33,
      "w": 32,
      "h": 32,
      "pivotX": 0,
      "pivotY": 0,
      "scaleX": 1.0,
      "scaleY": 1.0,
      "anchorToPointName": null,
      "anchorPoints": []
    },
    {
      "name": "TEXTURE_CONTROL_BACK_FAST",
      "x": 99,
      "y": 33,
      "w": 32,
      "h": 32,
      "pivotX": 0,
      "pivotY": 0,
      "scaleX": 1.0,
      "scaleY": 1.0,
      "anchorToPointName": null,
      "anchorPoints": []
    },
    {
      "name": "TEXTURE_CONTROL_CROSS",
      "x": 132,
      "y": 33,
      "w": 32,
      "h": 32,
      "pivotX": 0,
      "pivotY": 0,
      "scaleX": 1.0,
      "scaleY": 1.0,
      "anchorToPointName": null,
      "anchorPoints": []
    },
    {
      "name": "TEXTURE_CONTROL_DOWN",
      "x": 165,
      "y": 33,
      "w": 32,
      "h": 32,
      "pivotX": 0,
      "pivotY": 0,
      "scaleX": 1.0,
      "scaleY": 1.0,
      "anchorToPointName": null,
      "anchorPoints": []
    },
    {
      "name": "TEXTURE_CONTROL_EMPTY",
      "x": 198,
      "y": 33,
      "w": 32,
      "h": 32,
      "pivotX": 0,
      "pivotY": 0,
      "scaleX": 1.0,
      "scaleY": 1.0,
      "anchorToPointName": null,
      "anchorPoints": []
    },
    {
      "name": "TEXTURE_CONTROL_FORWARD_FAST",
      "x": 231,
      "y": 33,
      "w": 32,
      "h": 32,
      "pivotX": 0,
      "pivotY": 0,
      "scaleX": 1.0,
      "scaleY": 1.0,
      "anchorToPointName": null,
      "anchorPoints": []
    },
    {
      "name": "TEXTURE_CONTROL_INFO",
      "x": 264,
      "y": 33,
      "w": 32,
      "h": 32,
      "pivotX": 0,
      "pivotY": 0,
      "scaleX": 1.0,
      "scaleY": 1.0,
      "anchorToPointName": null,
      "anchorPoints": []
    },
    {
      "name": "TEXTURE_CONTROL_LEFT",
      "x": 297,
      "y": 33,
      "w": 32,
      "h": 32,
      "pivotX": 0,
      "pivotY": 0,
      "scaleX": 1.0,
      "scaleY": 1.0,
      "anchorToPointName": null,
      "anchorPoints": []
    },
    {
      "name": "TEXTURE_CONTROL_MINUS",
      "x": 330,
      "y": 33,
      "w": 32,
      "h": 32,
      "pivotX": 0,
      "pivotY": 0,
      "scaleX": 1.0,
      "scaleY": 1.0,
      "anchorToPointName": null,
      "anchorPoints": []
    },
    {
      "name": "TEXTURE_CONTROL_NEXT",
      "x": 363,
      "y": 33,
      "w": 32,
      "h": 32,
      "pivotX": 0,
      "pivotY": 0,
      "scaleX": 1.0,
      "scaleY": 1.0,
      "anchorToPointName": null,
      "anchorPoints": []
    },
    {
      "name": "TEXTURE_CONTROL_NUBBLE",
      "x": 396,
      "y": 33,
      "w": 32,
      "h": 32,
      "pivotX": 0,
      "pivotY": 0,
      "scaleX": 1.0,
      "scaleY": 1.0,
      "anchorToPointName": null,
      "anchorPoints": []
    },
    {
      "name": "TEXTURE_CONTROL_PAUSE",
      "x": 429,
      "y": 33,
      "w": 32,
      "h": 32,
      "pivotX": 0,
      "pivotY": 0,
      "scaleX": 1.0,
      "scaleY": 1.0,
      "anchorToPointName": null,
      "anchorPoints": []
    },
    {
      "name": "TEXTURE_CONTROL_PLAY",
      "x": 462,
      "y": 33,
      "w": 32,
      "h": 32,
      "pivotX": 0,
      "pivotY": 0,
      "scaleX": 1.0,
      "scaleY": 1.0,
      "anchorToPointName": null,
      "anchorPoints": []
    },
    {
      "name": "TEXTURE_CONTROL_PLUS",
      "x": 495,
      "y": 33,
      "w": 32,
      "h": 32,
      "pivotX": 0,
      "pivotY": 0,
      "scaleX": 1.0,
      "scaleY": 1.0,
      "anchorToPointName": null,
      "anchorPoints": []
    },
    {
      "name": "TEXTURE_CONTROL_PREV",
      "x": 528,
      "y": 33,
      "w": 32,
      "h": 32,
      "pivotX": 0,
      "pivotY": 0,
      "scaleX": 1.0,
      "scaleY": 1.0,
      "anchorToPointName": null,
      "anchorPoints": []
    },
    {
      "name": "TEXTURE_CONTROL_RIGHT",
      "x": 561,
      "y": 33,
      "w": 32,
      "h": 32,
      "pivotX": 0,
      "pivotY": 0,
      "scaleX": 1.0,
      "scaleY": 1.0,
      "anchorToPointName": null,
      "anchorPoints": []
    },
    {
      "name": "TEXTURE_CONTROL_SLIDER_HORIZONTAL_LEFT",
      "x": 594,
      "y": 33,
      "w": 32,
      "h": 32,
      "pivotX": 0,
      "pivotY": 0,
      "scaleX": 1.0,
      "scaleY": 1.0,
      "anchorToPointName": null,
      "anchorPoints": []
    },
    {
      "name": "TEXTURE_CONTROL_SLIDER_HORIZONTAL_MID",
      "x": 627,
      "y": 33,
      "w": 32,
      "h": 32,
      "pivotX": 0,
      "pivotY": 0,
      "scaleX": 1.0,
      "scaleY": 1.0,
      "anchorToPointName": null,
      "anchorPoints": []
    },
    {
      "name": "TEXTURE_CONTROL_SLIDER_HORIZONTAL_NUBBLE",
      "x": 660,
      "y": 33,
      "w": 32,
      "h": 32,
      "pivotX": 0,
      "pivotY": 0,
      "scaleX": 1.0,
      "scaleY": 1.0,
      "anchorToPointName": null,
      "anchorPoints": []
    },
    {
      "name": "TEXTURE_CONTROL_SLIDER_HORIZONTAL_RIGHT",
      "x": 693,
      "y": 33,
      "w": 32,
      "h": 32,
      "pivotX": 0,
      "pivotY": 0,
      "scaleX": 1.0,
      "scaleY": 1.0,
      "anchorToPointName": null,
      "anchorPoints": []
    },
    {
      "name": "TEXTURE_CONTROL_SLIDER_VERTICAL_BOTTOM",
      "x": 726,
      "y": 33,
      "w": 32,
      "h": 32,
      "pivotX": 0,
      "pivotY": 0,
      "scaleX": 1.0,
      "scaleY": 1.0,
      "anchorToPointName": null,
      "anchorPoints": []
    },
    {
      "name": "TEXTURE_CONTROL_SLIDER_VERTICAL_MID",
      "x": 759,
      "y": 33,
      "w": 32,
      "h": 32,
      "pivotX": 0,
      "pivotY": 0,
      "scaleX": 1.0,
      "scaleY": 1.0,
      "anchorToPointName": null,
      "anchorPoints": []
    },
    {
      "name": "TEXTURE_CONTROL_SLIDER_VERTICAL_NUBBLE",
      "x": 792,
      "y": 33,
      "w": 32,
      "h": 32,
      "pivotX": 0,
      "pivotY": 0,
      "scaleX": 1.0,
      "scaleY": 1.0,
      "anchorToPointName": null,
      "anchorPoints": []
    },
    {
      "name": "TEXTURE_CONTROL_SLIDER_VERTICAL_TOP",
      "x": 825,
      "y": 33,
      "w": 32,
      "h": 32,
      "pivotX": 0,
      "pivotY": 0,
      "scaleX": 1.0,
      "scaleY": 1.0,
      "anchorToPointName": null,
      "anchorPoints": []
    },
    {
      "name": "TEXTURE_CONTROL_STOP",
      "x": 858,
      "y": 33,
      "w": 32,
      "h": 32,
      "pivotX": 0,
      "pivotY": 0,
      "scaleX": 1.0,
      "scaleY": 1.0,
      "anchorToPointName": null,
      "anchorPoints": []
    },
    {
      "name": "TEXTURE_CONTROL_TICK",
      "x": 891,
      "y": 33,
      "w": 32,
      "h": 32,
      "pivotX": 0,
      "pivotY": 0,
      "scaleX": 1.0,
      "scaleY": 1.0,
      "anchorToPointName": null,
      "anchorPoints": []
    },
    {
      "name": "TEXTURE_CONTROL_UP",
      "x": 924,
      "y": 33,
      "w": 32,
      "h": 32,
      "pivotX": 0,
      "pivotY": 0,
      "scaleX": 1.0,
      "scaleY": 1.0,
      "anchorToPointName": null,
      "anchorPoints": []
    },
    {
      "name": "TEXTURE_CONTROL_WARNING",
      "x": 957,
      "y": 33,
      "w": 32,
      "h": 32,
      "pivotX": 0,
      "pivotY": 0,
      "scaleX": 1.0,
      "scaleY": 1.0,
      "anchorToPointName": null,
      "anchorPoints": []
    },
    {
      "name": "TEXTURE_CROSS",
      "x": 990,
      "y": 33,
      "w": 32,
      "h": 32,
      "pivotX": 0,
      "pivotY": 0,
      "scaleX": 1.0,
      "scaleY": 1.0,
      "anchorToPointName": null,
      "anchorPoints": []
    },
    {
      "name": "TEXTURE_ERASER",
      "x": 130,
      "y": 66,
      "w": 32,
      "h": 32,
      "pivotX": 0,
      "pivotY": 0,
      "scaleX": 1.0,
      "scaleY": 1.0,
      "anchorToPointName": null,
      "anchorPoints": []
    },
    {
      "name": "TEXTURE_EXPAND",
      "x": 163,
      "y": 66,
      "w": 32,
      "h": 32,
      "pivotX": 0,
      "pivotY": 0,
      "scaleX": 1.0,
      "scaleY": 1.0,
      "anchorToPointName": null,
      "anchorPoints": []
    },
    {
      "name": "TEXTURE_FOOTER_32X32",
      "x": 196,
      "y": 66,
      "w": 32,
      "h": 32,
      "pivotX": 0,
      "pivotY": 0,
      "scaleX": 1.0,
      "scaleY": 1.0,
      "anchorToPointName": null,
      "anchorPoints": []
    },
    {
      "name": "TEXTURE_GAMEPAD_A_DARK_COLOR",
      "x": 229,
      "y": 66,
      "w": 32,
      "h": 32,
      "pivotX": 0,
      "pivotY": 0,
      "scaleX": 1.0,
      "scaleY": 1.0,
      "anchorToPointName": null,
      "anchorPoints": []
    },
    {
      "name": "TEXTURE_GAMEPAD_A_DARK",
      "x": 262,
      "y": 66,
      "w": 32,
      "h": 32,
      "pivotX": 0,
      "pivotY": 0,
      "scaleX": 1.0,
      "scaleY": 1.0,
      "anchorToPointName": null,
      "anchorPoints": []
    },
    {
      "name": "TEXTURE_GAMEPAD_B_DARK_COLOR",
      "x": 295,
      "y": 66,
      "w": 32,
      "h": 32,
      "pivotX": 0,
      "pivotY": 0,
      "scaleX": 1.0,
      "scaleY": 1.0,
      "anchorToPointName": null,
      "anchorPoints": []
    },
    {
      "name": "TEXTURE_GAMEPAD_B_DARK",
      "x": 328,
      "y": 66,
      "w": 32,
      "h": 32,
      "pivotX": 0,
      "pivotY": 0,
      "scaleX": 1.0,
      "scaleY": 1.0,
      "anchorToPointName": null,
      "anchorPoints": []
    },
    {
      "name": "TEXTURE_GAMEPAD_DOWN_DARK",
      "x": 361,
      "y": 66,
      "w": 32,
      "h": 32,
      "pivotX": 0,
      "pivotY": 0,
      "scaleX": 1.0,
      "scaleY": 1.0,
      "anchorToPointName": null,
      "anchorPoints": []
    },
    {
      "name": "TEXTURE_GAMEPAD_DOWN_LIGHT",
      "x": 394,
      "y": 66,
      "w": 32,
      "h": 32,
      "pivotX": 0,
      "pivotY": 0,
      "scaleX": 1.0,
      "scaleY": 1.0,
      "anchorToPointName": null,
      "anchorPoints": []
    },
    {
      "name": "TEXTURE_GAMEPAD_L_DARK",
      "x": 427,
      "y": 66,
      "w": 32,
      "h": 32,
      "pivotX": 0,
      "pivotY": 0,
      "scaleX": 1.0,
      "scaleY": 1.0,
      "anchorToPointName": null,
      "anchorPoints": []
    },
    {
      "name": "TEXTURE_GAMEPAD_L_LIGHT",
      "x": 460,
      "y": 66,
      "w": 32,
      "h": 32,
      "pivotX": 0,
      "pivotY": 0,
      "scaleX": 1.0,
      "scaleY": 1.0,
      "anchorToPointName": null,
      "anchorPoints": []
    },
    {
      "name": "TEXTURE_GAMEPAD_LEFT_DARK",
      "x": 591,
      "y": 66,
      "w": 32,
      "h": 32,
      "pivotX": 0,
      "pivotY": 0,
      "scaleX": 1.0,
      "scaleY": 1.0,
      "anchorToPointName": null,
      "anchorPoints": []
    },
    {
      "name": "TEXTURE_GAMEPAD_LEFT_LIGHT",
      "x": 624,
      "y": 66,
      "w": 32,
      "h": 32,
      "pivotX": 0,
      "pivotY": 0,
      "scaleX": 1.0,
      "scaleY": 1.0,
      "anchorToPointName": null,
      "anchorPoints": []
    },
    {
      "name": "TEXTURE_GAMEPAD_R_DARK",
      "x": 755,
      "y": 66,
      "w": 32,
      "h": 32,
      "pivotX": 0,
      "pivotY": 0,
      "scaleX": 1.0,
      "scaleY": 1.0,
      "anchorToPointName": null,
      "anchorPoints": []
    },
    {
      "name": "TEXTURE_GAMEPAD_R_LIGHT",
      "x": 788,
      "y": 66,
      "w": 32,
      "h": 32,
      "pivotX": 0,
      "pivotY": 0,
      "scaleX": 1.0,
      "scaleY": 1.0,
      "anchorToPointName": null,
      "anchorPoints": []
    },
    {
      "name": "TEXTURE_GAMEPAD_RIGHT_DARK",
      "x": 919,
      "y": 66,
      "w": 32,
      "h": 32,
      "pivotX": 0,
      "pivotY": 0,
      "scaleX": 1.0,
      "scaleY": 1.0,
      "anchorToPointName": null,
      "anchorPoints": []
    },
    {
      "name": "TEXTURE_GAMEPAD_RIGHT_LIGHT",
      "x": 952,
      "y": 66,
      "w": 32,
      "h": 32,
      "pivotX": 0,
      "pivotY": 0,
      "scaleX": 1.0,
      "scaleY": 1.0,
      "anchorToPointName": null,
      "anchorPoints": []
    },
    {
      "name": "TEXTURE_GAMEPAD_SELECT_DARK",
      "x": 985,
      "y": 66,
      "w": 32,
      "h": 32,
      "pivotX": 0,
      "pivotY": 0,
      "scaleX": 1.0,
      "scaleY": 1.0,
      "anchorToPointName": null,
      "anchorPoints": []
    },
    {
      "name": "TEXTURE_GAMEPAD_SELECT_LIGHT",
      "x": 293,
      "y": 131,
      "w": 32,
      "h": 32,
      "pivotX": 0,
      "pivotY": 0,
      "scaleX": 1.0,
      "scaleY": 1.0,
      "anchorToPointName": null,
      "anchorPoints": []
    },
    {
      "name": "TEXTURE_GAMEPAD_UP_DARK",
      "x": 326,
      "y": 131,
      "w": 32,
      "h": 32,
      "pivotX": 0,
      "pivotY": 0,
      "scaleX": 1.0,
      "scaleY": 1.0,
      "anchorToPointName": null,
      "anchorPoints": []
    },
    {
      "name": "TEXTURE_GAMEPAD_UP_LIGHT",
      "x": 359,
      "y": 131,
      "w": 32,
      "h": 32,
      "pivotX": 0,
      "pivotY": 0,
      "scaleX": 1.0,
      "scaleY": 1.0,
      "anchorToPointName": null,
      "anchorPoints": []
    },
    {
      "name": "TEXTURE_GAMEPAD_VIEW_DARK",
      "x": 392,
      "y": 131,
      "w": 32,
      "h": 32,
      "pivotX": 0,
      "pivotY": 0,
      "scaleX": 1.0,
      "scaleY": 1.0,
      "anchorToPointName": null,
      "anchorPoints": []
    },
    {
      "name": "TEXTURE_GAMEPAD_VIEW_LIGHT",
      "x": 425,
      "y": 131,
      "w": 32,
      "h": 32,
      "pivotX": 0,
      "pivotY": 0,
      "scaleX": 1.0,
      "scaleY": 1.0,
      "anchorToPointName": null,
      "anchorPoints": []
    },
    {
      "name": "TEXTURE_GAMEPAD_X_DARK_COLOR",
      "x": 458,
      "y": 131,
      "w": 32,
      "h": 32,
      "pivotX": 0,
      "pivotY": 0,
      "scaleX": 1.0,
      "scaleY": 1.0,
      "anchorToPointName": null,
      "anchorPoints": []
    },
    {
      "name": "TEXTURE_GAMEPAD_X_DARK",
      "x": 491,
      "y": 131,
      "w": 32,
      "h": 32,
      "pivotX": 0,
      "pivotY": 0,
      "scaleX": 1.0,
      "scaleY": 1.0,
      "anchorToPointName": null,
      "anchorPoints": []
    },
    {
      "name": "TEXTURE_GAMEPAD_Y_DARK_COLOR",
      "x": 524,
      "y": 131,
      "w": 32,
      "h": 32,
      "pivotX": 0,
      "pivotY": 0,
      "scaleX": 1.0,
      "scaleY": 1.0,
      "anchorToPointName": null,
      "anchorPoints": []
    },
    {
      "name": "TEXTURE_GAMEPAD_Y_DARK",
      "x": 557,
      "y": 131,
      "w": 32,
      "h": 32,
      "pivotX": 0,
      "pivotY": 0,
      "scaleX": 1.0,
      "scaleY": 1.0,
      "anchorToPointName": null,
      "anchorPoints": []
    },
    {
      "name": "TEXTURE_KEY_SMALL",
      "x": 776,
      "y": 131,
      "w": 32,
      "h": 32,
      "pivotX": 0,
      "pivotY": 0,
      "scaleX": 1.0,
      "scaleY": 1.0,
      "anchorToPointName": null,
      "anchorPoints": []
    },
    {
      "name": "TEXTURE_MENU_BUTTON_HORIZONTAL_LEFT",
      "x": 809,
      "y": 131,
      "w": 32,
      "h": 32,
      "pivotX": 0,
      "pivotY": 0,
      "scaleX": 1.0,
      "scaleY": 1.0,
      "anchorToPointName": null,
      "anchorPoints": []
    },
    {
      "name": "TEXTURE_MENU_BUTTON_HORIZONTAL_MID",
      "x": 842,
      "y": 131,
      "w": 32,
      "h": 32,
      "pivotX": 0,
      "pivotY": 0,
      "scaleX": 1.0,
      "scaleY": 1.0,
      "anchorToPointName": null,
      "anchorPoints": []
    },
    {
      "name": "TEXTURE_MENU_BUTTON_HORIZONTAL_MIDLEFT",
      "x": 875,
      "y": 131,
      "w": 32,
      "h": 32,
      "pivotX": 0,
      "pivotY": 0,
      "scaleX": 1.0,
      "scaleY": 1.0,
      "anchorToPointName": null,
      "anchorPoints": []
    },
    {
      "name": "TEXTURE_MENU_BUTTON_HORIZONTAL_MIDRIGHT",
      "x": 908,
      "y": 131,
      "w": 32,
      "h": 32,
      "pivotX": 0,
      "pivotY": 0,
      "scaleX": 1.0,
      "scaleY": 1.0,
      "anchorToPointName": null,
      "anchorPoints": []
    },
    {
      "name": "TEXTURE_MENU_BUTTON_HORIZONTAL_RIGHT",
      "x": 941,
      "y": 131,
      "w": 32,
      "h": 32,
      "pivotX": 0,
      "pivotY": 0,
      "scaleX": 1.0,
      "scaleY": 1.0,
      "anchorToPointName": null,
      "anchorPoints": []
    },
    {
      "name": "TEXTURE_MENU_INPUT_FIELD_LEFT",
      "x": 974,
      "y": 131,
      "w": 32,
      "h": 32,
      "pivotX": 0,
      "pivotY": 0,
      "scaleX": 1.0,
      "scaleY": 1.0,
      "anchorToPointName": null,
      "anchorPoints": []
    },
    {
      "name": "TEXTURE_MENU_INPUT_FIELD_MID",
      "x": 421,
      "y": 196,
      "w": 32,
      "h": 32,
      "pivotX": 0,
      "pivotY": 0,
      "scaleX": 1.0,
      "scaleY": 1.0,
      "anchorToPointName": null,
      "anchorPoints": []
    },
    {
      "name": "TEXTURE_MENU_INPUT_FIELD_RIGHT",
      "x": 454,
      "y": 196,
      "w": 32,
      "h": 32,
      "pivotX": 0,
      "pivotY": 0,
      "scaleX": 1.0,
      "scaleY": 1.0,
      "anchorToPointName": null,
      "anchorPoints": []
    },
    {
      "name": "TEXTURE_MENU_LABEL_LEFT",
      "x": 487,
      "y": 196,
      "w": 32,
      "h": 32,
      "pivotX": 0,
      "pivotY": 0,
      "scaleX": 1.0,
      "scaleY": 1.0,
      "anchorToPointName": null,
      "anchorPoints": []
    },
    {
      "name": "TEXTURE_MENU_LABEL_MID",
      "x": 520,
      "y": 196,
      "w": 32,
      "h": 32,
      "pivotX": 0,
      "pivotY": 0,
      "scaleX": 1.0,
      "scaleY": 1.0,
      "anchorToPointName": null,
      "anchorPoints": []
    },
    {
      "name": "TEXTURE_MENU_LABEL_RIGHT",
      "x": 553,
      "y": 196,
      "w": 32,
      "h": 32,
      "pivotX": 0,
      "pivotY": 0,
      "scaleX": 1.0,
      "scaleY": 1.0,
      "anchorToPointName": null,
      "anchorPoints": []
    },
    {
      "name": "TEXTURE_OUTLINE_MEDIUM",
      "x": 586,
      "y": 196,
      "w": 32,
      "h": 32,
      "pivotX": 0,
      "pivotY": 0,
      "scaleX": 1.0,
      "scaleY": 1.0,
      "anchorToPointName": null,
      "anchorPoints": []
    },
    {
      "name": "TEXTURE_PANEL_1X3_BOTTOM",
      "x": 619,
      "y": 196,
      "w": 32,
      "h": 32,
      "pivotX": 0,
      "pivotY": 0,
      "scaleX": 1.0,
      "scaleY": 1.0,
      "anchorToPointName": null,
      "anchorPoints": []
    },
    {
      "name": "TEXTURE_PANEL_1X3_MID",
      "x": 652,
      "y": 196,
      "w": 32,
      "h": 32,
      "pivotX": 0,
      "pivotY": 0,
      "scaleX": 1.0,
      "scaleY": 1.0,
      "anchorToPointName": null,
      "anchorPoints": []
    },
    {
      "name": "TEXTURE_PANEL_1X3_TOP",
      "x": 685,
      "y": 196,
      "w": 32,
      "h": 32,
      "pivotX": 0,
      "pivotY": 0,
      "scaleX": 1.0,
      "scaleY": 1.0,
      "anchorToPointName": null,
      "anchorPoints": []
    },
    {
      "name": "TEXTURE_PANEL_2X2_BOTTOM_LEFT",
      "x": 718,
      "y": 196,
      "w": 32,
      "h": 32,
      "pivotX": 0,
      "pivotY": 0,
      "scaleX": 1.0,
      "scaleY": 1.0,
      "anchorToPointName": null,
      "anchorPoints": []
    },
    {
      "name": "TEXTURE_PANEL_2X2_BOTTOM_RIGHT",
      "x": 751,
      "y": 196,
      "w": 32,
      "h": 32,
      "pivotX": 0,
      "pivotY": 0,
      "scaleX": 1.0,
      "scaleY": 1.0,
      "anchorToPointName": null,
      "anchorPoints": []
    },
    {
      "name": "TEXTURE_PANEL_2X2_TOP_LEFT",
      "x": 784,
      "y": 196,
      "w": 32,
      "h": 32,
      "pivotX": 0,
      "pivotY": 0,
      "scaleX": 1.0,
      "scaleY": 1.0,
      "anchorToPointName": null,
      "anchorPoints": []
    },
    {
      "name": "TEXTURE_PANEL_2X2_TOP_RIGHT",
      "x": 817,
      "y": 196,
      "w": 32,
      "h": 32,
      "pivotX": 0,
      "pivotY": 0,
      "scaleX": 1.0,
      "scaleY": 1.0,
      "anchorToPointName": null,
      "anchorPoints": []
    },
    {
      "name": "TEXTURE_PANEL_2X3_BOTTOM_LEFT",
      "x": 850,
      "y": 196,
      "w": 32,
      "h": 32,
      "pivotX": 0,
      "pivotY": 0,
      "scaleX": 1.0,
      "scaleY": 1.0,
      "anchorToPointName": null,
      "anchorPoints": []
    },
    {
      "name": "TEXTURE_PANEL_2X3_BOTTOM_RIGHT",
      "x": 883,
      "y": 196,
      "w": 32,
      "h": 32,
      "pivotX": 0,
      "pivotY": 0,
      "scaleX": 1.0,
      "scaleY": 1.0,
      "anchorToPointName": null,
      "anchorPoints": []
    },
    {
      "name": "TEXTURE_PANEL_2X3_MIDLEFT",
      "x": 916,
      "y": 196,
      "w": 32,
      "h": 32,
      "pivotX": 0,
      "pivotY": 0,
      "scaleX": 1.0,
      "scaleY": 1.0,
      "anchorToPointName": null,
      "anchorPoints": []
    },
    {
      "name": "TEXTURE_PANEL_2X3_MIDRIGHT",
      "x": 949,
      "y": 196,
      "w": 32,
      "h": 32,
      "pivotX": 0,
      "pivotY": 0,
      "scaleX": 1.0,
      "scaleY": 1.0,
      "anchorToPointName": null,
      "anchorPoints": []
    },
    {
      "name": "TEXTURE_PANEL_2X3_TOP_LEFT",
      "x": 982,
      "y": 196,
      "w": 32,
      "h": 32,
      "pivotX": 0,
      "pivotY": 0,
      "scaleX": 1.0,
      "scaleY": 1.0,
      "anchorToPointName": null,
      "anchorPoints": []
    },
    {
      "name": "TEXTURE_PANEL_2X3_TOP_RIGHT",
      "x": 65,
      "y": 293,
      "w": 32,
      "h": 32,
      "pivotX": 0,
      "pivotY": 0,
      "scaleX": 1.0,
      "scaleY": 1.0,
      "anchorToPointName": null,
      "anchorPoints": []
    },
    {
      "name": "TEXTURE_PANEL_3X1_LEFT",
      "x": 98,
      "y": 293,
      "w": 32,
      "h": 32,
      "pivotX": 0,
      "pivotY": 0,
      "scaleX": 1.0,
      "scaleY": 1.0,
      "anchorToPointName": null,
      "anchorPoints": []
    },
    {
      "name": "TEXTURE_PANEL_3X1_MID",
      "x": 131,
      "y": 293,
      "w": 32,
      "h": 32,
      "pivotX": 0,
      "pivotY": 0,
      "scaleX": 1.0,
      "scaleY": 1.0,
      "anchorToPointName": null,
      "anchorPoints": []
    },
    {
      "name": "TEXTURE_PANEL_3X1_RIGHT",
      "x": 164,
      "y": 293,
      "w": 32,
      "h": 32,
      "pivotX": 0,
      "pivotY": 0,
      "scaleX": 1.0,
      "scaleY": 1.0,
      "anchorToPointName": null,
      "anchorPoints": []
    },
    {
      "name": "TEXTURE_PANEL_3X2_BOTTOM_LEFT",
      "x": 197,
      "y": 293,
      "w": 32,
      "h": 32,
      "pivotX": 0,
      "pivotY": 0,
      "scaleX": 1.0,
      "scaleY": 1.0,
      "anchorToPointName": null,
      "anchorPoints": []
    },
    {
      "name": "TEXTURE_PANEL_3X2_BOTTOM_MID",
      "x": 230,
      "y": 293,
      "w": 32,
      "h": 32,
      "pivotX": 0,
      "pivotY": 0,
      "scaleX": 1.0,
      "scaleY": 1.0,
      "anchorToPointName": null,
      "anchorPoints": []
    },
    {
      "name": "TEXTURE_PANEL_3X2_BOTTOM_RIGHT",
      "x": 263,
      "y": 293,
      "w": 32,
      "h": 32,
      "pivotX": 0,
      "pivotY": 0,
      "scaleX": 1.0,
      "scaleY": 1.0,
      "anchorToPointName": null,
      "anchorPoints": []
    },
    {
      "name": "TEXTURE_PANEL_3X2_TOP_LEFT",
      "x": 296,
      "y": 293,
      "w": 32,
      "h": 32,
      "pivotX": 0,
      "pivotY": 0,
      "scaleX": 1.0,
      "scaleY": 1.0,
      "anchorToPointName": null,
      "anchorPoints": []
    },
    {
      "name": "TEXTURE_PANEL_3X2_TOP_MID",
      "x": 329,
      "y": 293,
      "w": 32,
      "h": 32,
      "pivotX": 0,
      "pivotY": 0,
      "scaleX": 1.0,
      "scaleY": 1.0,
      "anchorToPointName": null,
      "anchorPoints": []
    },
    {
      "name": "TEXTURE_PANEL_3X2_TOP_RIGHT",
      "x": 362,
      "y": 293,
      "w": 32,
      "h": 32,
      "pivotX": 0,
      "pivotY": 0,
      "scaleX": 1.0,
      "scaleY": 1.0,
      "anchorToPointName": null,
      "anchorPoints": []
    },
    {
      "name": "TEXTURE_PANEL_3X3_00_BOTTOM_LEFT",
      "x": 395,
      "y": 293,
      "w": 32,
      "h": 32,
      "pivotX": 0,
      "pivotY": 0,
      "scaleX": 1.0,
      "scaleY": 1.0,
      "anchorToPointName": null,
      "anchorPoints": []
    },
    {
      "name": "TEXTURE_PANEL_3X3_00_BOTTOM_MID",
      "x": 428,
      "y": 293,
      "w": 32,
      "h": 32,
      "pivotX": 0,
      "pivotY": 0,
      "scaleX": 1.0,
      "scaleY": 1.0,
      "anchorToPointName": null,
      "anchorPoints": []
    },
    {
      "name": "TEXTURE_PANEL_3X3_00_BOTTOM_RIGHT",
      "x": 461,
      "y": 293,
      "w": 32,
      "h": 32,
      "pivotX": 0,
      "pivotY": 0,
      "scaleX": 1.0,
      "scaleY": 1.0,
      "anchorToPointName": null,
      "anchorPoints": []
    },
    {
      "name": "TEXTURE_PANEL_3X3_00_MID_CENTER",
      "x": 494,
      "y": 293,
      "w": 32,
      "h": 32,
      "pivotX": 0,
      "pivotY": 0,
      "scaleX": 1.0,
      "scaleY": 1.0,
      "anchorToPointName": null,
      "anchorPoints": []
    },
    {
      "name": "TEXTURE_PANEL_3X3_00_MID_LEFT",
      "x": 527,
      "y": 293,
      "w": 32,
      "h": 32,
      "pivotX": 0,
      "pivotY": 0,
      "scaleX": 1.0,
      "scaleY": 1.0,
      "anchorToPointName": null,
      "anchorPoints": []
    },
    {
      "name": "TEXTURE_PANEL_3X3_00_MID_RIGHT",
      "x": 560,
      "y": 293,
      "w": 32,
      "h": 32,
      "pivotX": 0,
      "pivotY": 0,
      "scaleX": 1.0,
      "scaleY": 1.0,
      "anchorToPointName": null,
      "anchorPoints": []
    },
    {
      "name": "TEXTURE_PANEL_3X3_00_TOP_LEFT",
      "x": 593,
      "y": 293,
      "w": 32,
      "h": 32,
      "pivotX": 0,
      "pivotY": 0,
      "scaleX": 1.0,
      "scaleY": 1.0,
      "anchorToPointName": null,
      "anchorPoints": []
    },
    {
      "name": "TEXTURE_PANEL_3X3_00_TOP_MID",
      "x": 626,
      "y": 293,
      "w": 32,
      "h": 32,
      "pivotX": 0,
      "pivotY": 0,
      "scaleX": 1.0,
      "scaleY": 1.0,
      "anchorToPointName": null,
      "anchorPoints": []
    },
    {
      "name": "TEXTURE_PANEL_3X3_00_TOP_RIGHT",
      "x": 659,
      "y": 293,
      "w": 32,
      "h": 32,
      "pivotX": 0,
      "pivotY": 0,
      "scaleX": 1.0,
      "scaleY": 1.0,
      "anchorToPointName": null,
      "anchorPoints": []
    },
    {
      "name": "TEXTURE_PANEL_3X3_01_BOTTOM_LEFT",
      "x": 692,
      "y": 293,
      "w": 32,
      "h": 32,
      "pivotX": 0,
      "pivotY": 0,
      "scaleX": 1.0,
      "scaleY": 1.0,
      "anchorToPointName": null,
      "anchorPoints": []
    },
    {
      "name": "TEXTURE_PANEL_3X3_01_BOTTOM_MID",
      "x": 725,
      "y": 293,
      "w": 32,
      "h": 32,
      "pivotX": 0,
      "pivotY": 0,
      "scaleX": 1.0,
      "scaleY": 1.0,
      "anchorToPointName": null,
      "anchorPoints": []
    },
    {
      "name": "TEXTURE_PANEL_3X3_01_BOTTOM_RIGHT",
      "x": 758,
      "y": 293,
      "w": 32,
      "h": 32,
      "pivotX": 0,
      "pivotY": 0,
      "scaleX": 1.0,
      "scaleY": 1.0,
      "anchorToPointName": null,
      "anchorPoints": []
    },
    {
      "name": "TEXTURE_PANEL_3X3_01_MID_CENTER",
      "x": 791,
      "y": 293,
      "w": 32,
      "h": 32,
      "pivotX": 0,
      "pivotY": 0,
      "scaleX": 1.0,
      "scaleY": 1.0,
      "anchorToPointName": null,
      "anchorPoints": []
    },
    {
      "name": "TEXTURE_PANEL_3X3_01_MID_LEFT",
      "x": 824,
      "y": 293,
      "w": 32,
      "h": 32,
      "pivotX": 0,
      "pivotY": 0,
      "scaleX": 1.0,
      "scaleY": 1.0,
      "anchorToPointName": null,
      "anchorPoints": []
    },
    {
      "name": "TEXTURE_PANEL_3X3_01_MID_RIGHT",
      "x": 857,
      "y": 293,
      "w": 32,
      "h": 32,
      "pivotX": 0,
      "pivotY": 0,
      "scaleX": 1.0,
      "scaleY": 1.0,
      "anchorToPointName": null,
      "anchorPoints": []
    },
    {
      "name": "TEXTURE_PANEL_3X3_01_TOP_LEFT",
      "x": 890,
      "y": 293,
      "w": 32,
      "h": 32,
      "pivotX": 0,
      "pivotY": 0,
      "scaleX": 1.0,
      "scaleY": 1.0,
      "anchorToPointName": null,
      "anchorPoints": []
    },
    {
      "name": "TEXTURE_PANEL_3X3_01_TOP_MID",
      "x": 923,
      "y": 293,
      "w": 32,
      "h": 32,
      "pivotX": 0,
      "pivotY": 0,
      "scaleX": 1.0,
      "scaleY": 1.0,
      "anchorToPointName": null,
      "anchorPoints": []
    },
    {
      "name": "TEXTURE_PANEL_3X3_01_TOP_RIGHT",
      "x": 956,
      "y": 293,
      "w": 32,
      "h": 32,
      "pivotX": 0,
      "pivotY": 0,
      "scaleX": 1.0,
      "scaleY": 1.0,
      "anchorToPointName": null,
      "anchorPoints": []
    },
    {
      "name": "TEXTURE_PROGRESS_BAR_3X1_INNER_LEFT",
      "x": 989,
      "y": 293,
      "w": 32,
      "h": 32,
      "pivotX": 0,
      "pivotY": 0,
      "scaleX": 1.0,
      "scaleY": 1.0,
      "anchorToPointName": null,
      "anchorPoints": []
    },
    {
      "name": "TEXTURE_PROGRESS_BAR_3X1_INNER_MID",
      "x": 0,
      "y": 358,
      "w": 32,
      "h": 32,
      "pivotX": 0,
      "pivotY": 0,
      "scaleX": 1.0,
      "scaleY": 1.0,
      "anchorToPointName": null,
      "anchorPoints": []
    },
    {
      "name": "TEXTURE_PROGRESS_BAR_3X1_INNER_RIGHT",
      "x": 33,
      "y": 358,
      "w": 32,
      "h": 32,
      "pivotX": 0,
      "pivotY": 0,
      "scaleX": 1.0,
      "scaleY": 1.0,
      "anchorToPointName": null,
      "anchorPoints": []
    },
    {
      "name": "TEXTURE_PROGRESS_BAR_3X1_OUTER_LEFT",
      "x": 66,
      "y": 358,
      "w": 32,
      "h": 32,
      "pivotX": 0,
      "pivotY": 0,
      "scaleX": 1.0,
      "scaleY": 1.0,
      "anchorToPointName": null,
      "anchorPoints": []
    },
    {
      "name": "TEXTURE_PROGRESS_BAR_3X1_OUTER_MID",
      "x": 99,
      "y": 358,
      "w": 32,
      "h": 32,
      "pivotX": 0,
      "pivotY": 0,
      "scaleX": 1.0,
      "scaleY": 1.0,
      "anchorToPointName": null,
      "anchorPoints": []
    },
    {
      "name": "TEXTURE_PROGRESS_BAR_3X1_OUTER_RIGHT",
      "x": 132,
      "y": 358,
      "w": 32,
      "h": 32,
      "pivotX": 0,
      "pivotY": 0,
      "scaleX": 1.0,
      "scaleY": 1.0,
      "anchorToPointName": null,
      "anchorPoints": []
    },
    {
      "name": "TEXTURE_SELECTED_MEDIUM",
      "x": 165,
      "y": 358,
      "w": 32,
      "h": 32,
      "pivotX": 0,
      "pivotY": 0,
      "scaleX": 1.0,
      "scaleY": 1.0,
      "anchorToPointName": null,
      "anchorPoints": []
    },
    {
      "name": "TEXTURE_TICK",
      "x": 198,
      "y": 358,
      "w": 32,
      "h": 32,
      "pivotX": 0,
      "pivotY": 0,
      "scaleX": 1.0,
      "scaleY": 1.0,
      "anchorToPointName": null,
      "anchorPoints": []
    },
    {
      "name": "TEXTURE_TITLE_HORIZONTAL_LEFT",
      "x": 231,
      "y": 358,
      "w": 32,
      "h": 32,
      "pivotX": 0,
      "pivotY": 0,
      "scaleX": 1.0,
      "scaleY": 1.0,
      "anchorToPointName": null,
      "anchorPoints": []
    },
    {
      "name": "TEXTURE_TITLE_HORIZONTAL_MID_LEFT",
      "x": 264,
      "y": 358,
      "w": 32,
      "h": 32,
      "pivotX": 0,
      "pivotY": 0,
      "scaleX": 1.0,
      "scaleY": 1.0,
      "anchorToPointName": null,
      "anchorPoints": []
    },
    {
      "name": "TEXTURE_TITLE_HORIZONTAL_MID_RIGHT",
      "x": 297,
      "y": 358,
      "w": 32,
      "h": 32,
      "pivotX": 0,
      "pivotY": 0,
      "scaleX": 1.0,
      "scaleY": 1.0,
      "anchorToPointName": null,
      "anchorPoints": []
    },
    {
      "name": "TEXTURE_TITLE_HORIZONTAL_MID",
      "x": 330,
      "y": 358,
      "w": 32,
      "h": 32,
      "pivotX": 0,
      "pivotY": 0,
      "scaleX": 1.0,
      "scaleY": 1.0,
      "anchorToPointName": null,
      "anchorPoints": []
    },
    {
      "name": "TEXTURE_TITLE_HORIZONTAL_RIGHT",
      "x": 363,
      "y": 358,
      "w": 32,
      "h": 32,
      "pivotX": 0,
      "pivotY": 0,
      "scaleX": 1.0,
      "scaleY": 1.0,
      "anchorToPointName": null,
      "anchorPoints": []
    },
    {
      "name": "TEXTURE_WIDGET_LEFT_ARROW",
      "x": 396,
      "y": 358,
      "w": 32,
      "h": 32,
      "pivotX": 0,
      "pivotY": 0,
      "scaleX": 1.0,
      "scaleY": 1.0,
      "anchorToPointName": null,
      "anchorPoints": []
    },
    {
      "name": "TEXTURE_WIDGET_RIGHT_ARROW",
      "x": 429,
      "y": 358,
      "w": 32,
      "h": 32,
      "pivotX": 0,
      "pivotY": 0,
      "scaleX": 1.0,
      "scaleY": 1.0,
      "anchorToPointName": null,
      "anchorPoints": []
    },
    {
      "name": "TEXTUREDIRECTORY",
      "x": 462,
      "y": 358,
      "w": 32,
      "h": 32,
      "pivotX": 0,
      "pivotY": 0,
      "scaleX": 1.0,
      "scaleY": 1.0,
      "anchorToPointName": null,
      "anchorPoints": []
    },
    {
      "name": "TEXTUREDIRECTORYASSETS",
      "x": 495,
      "y": 358,
      "w": 32,
      "h": 32,
      "pivotX": 0,
      "pivotY": 0,
      "scaleX": 1.0,
      "scaleY": 1.0,
      "anchorToPointName": null,
      "anchorPoints": []
    },
    {
      "name": "TEXTURERANDOM",
      "x": 528,
      "y": 358,
      "w": 32,
      "h": 32,
      "pivotX": 0,
      "pivotY": 0,
      "scaleX": 1.0,
      "scaleY": 1.0,
      "anchorToPointName": null,
      "anchorPoints": []
    },
    {
      "name": "TEXTURE_BLACK",
      "x": 33,
      "y": 0,
      "w": 16,
      "h": 16,
      "pivotX": 0,
      "pivotY": 0,
      "scaleX": 1.0,
      "scaleY": 1.0,
      "anchorToPointName": null,
      "anchorPoints": []
    },
    {
      "name": "TEXTURE_BLUE",
      "x": 50,
      "y": 0,
      "w": 16,
      "h": 16,
      "pivotX": 0,
      "pivotY": 0,
      "scaleX": 1.0,
      "scaleY": 1.0,
      "anchorToPointName": null,
      "anchorPoints": []
    },
    {
      "name": "TEXTURE_DESELECTED_SMALL",
      "x": 67,
      "y": 0,
      "w": 16,
      "h": 16,
      "pivotX": 0,
      "pivotY": 0,
      "scaleX": 1.0,
      "scaleY": 1.0,
      "anchorToPointName": null,
      "anchorPoints": []
    },
    {
      "name": "TEXTURE_ENTRY_HIGHLIGHT_CORNER_BL",
      "x": 84,
      "y": 0,
      "w": 16,
      "h": 16,
      "pivotX": 0,
      "pivotY": 0,
      "scaleX": 1.0,
      "scaleY": 1.0,
      "anchorToPointName": null,
      "anchorPoints": []
    },
    {
      "name": "TEXTURE_ENTRY_HIGHLIGHT_CORNER_BR",
      "x": 101,
      "y": 0,
      "w": 16,
      "h": 16,
      "pivotX": 0,
      "pivotY": 0,
      "scaleX": 1.0,
      "scaleY": 1.0,
      "anchorToPointName": null,
      "anchorPoints": []
    },
    {
      "name": "TEXTURE_ENTRY_HIGHLIGHT_CORNER_TL",
      "x": 118,
      "y": 0,
      "w": 16,
      "h": 16,
      "pivotX": 0,
      "pivotY": 0,
      "scaleX": 1.0,
      "scaleY": 1.0,
      "anchorToPointName": null,
      "anchorPoints": []
    },
    {
      "name": "TEXTURE_ENTRY_HIGHLIGHT_CORNER_TR",
      "x": 135,
      "y": 0,
      "w": 16,
      "h": 16,
      "pivotX": 0,
      "pivotY": 0,
      "scaleX": 1.0,
      "scaleY": 1.0,
      "anchorToPointName": null,
      "anchorPoints": []
    },
    {
      "name": "TEXTURE_GREEN",
      "x": 152,
      "y": 0,
      "w": 16,
      "h": 16,
      "pivotX": 0,
      "pivotY": 0,
      "scaleX": 1.0,
      "scaleY": 1.0,
      "anchorToPointName": null,
      "anchorPoints": []
    },
    {
      "name": "TEXTURE_OUTLINE_SMALL",
      "x": 169,
      "y": 0,
      "w": 16,
      "h": 16,
      "pivotX": 0,
      "pivotY": 0,
      "scaleX": 1.0,
      "scaleY": 1.0,
      "anchorToPointName": null,
      "anchorPoints": []
    },
    {
      "name": "TEXTURE_RED",
      "x": 186,
      "y": 0,
      "w": 16,
      "h": 16,
      "pivotX": 0,
      "pivotY": 0,
      "scaleX": 1.0,
      "scaleY": 1.0,
      "anchorToPointName": null,
      "anchorPoints": []
    },
    {
      "name": "TEXTURE_SCROLLBAR_DOWN",
      "x": 203,
      "y": 0,
      "w": 16,
      "h": 16,
      "pivotX": 0,
      "pivotY": 0,
      "scaleX": 1.0,
      "scaleY": 1.0,
      "anchorToPointName": null,
      "anchorPoints": []
    },
    {
      "name": "TEXTURE_SCROLLBAR_LEFT",
      "x": 220,
      "y": 0,
      "w": 16,
      "h": 16,
      "pivotX": 0,
      "pivotY": 0,
      "scaleX": 1.0,
      "scaleY": 1.0,
      "anchorToPointName": null,
      "anchorPoints": []
    },
    {
      "name": "TEXTURE_SCROLLBAR_RIGHT",
      "x": 237,
      "y": 0,
      "w": 16,
      "h": 16,
      "pivotX": 0,
      "pivotY": 0,
      "scaleX": 1.0,
      "scaleY": 1.0,
      "anchorToPointName": null,
      "anchorPoints": []
    },
    {
      "name": "TEXTURE_SCROLLBAR_UP",
      "x": 254,
      "y": 0,
      "w": 16,
      "h": 16,
      "pivotX": 0,
      "pivotY": 0,
      "scaleX": 1.0,
      "scaleY": 1.0,
      "anchorToPointName": null,
      "anchorPoints": []
    },
    {
      "name": "TEXTURE_SELECTED_SMALL",
      "x": 271,
      "y": 0,
      "w": 16,
      "h": 16,
      "pivotX": 0,
      "pivotY": 0,
      "scaleX": 1.0,
      "scaleY": 1.0,
      "anchorToPointName": null,
      "anchorPoints": []
    },
    {
      "name": "TEXTURE_WHITE",
      "x": 288,
      "y": 0,
      "w": 16,
      "h": 16,
      "pivotX": 0,
      "pivotY": 0,
      "scaleX": 1.0,
      "scaleY": 1.0,
      "anchorToPointName": null,
      "anchorPoints": []
    },
    {
      "name": "TEXTURE_KEY_END_LEFT",
      "x": 590,
      "y": 131,
      "w": 7,
      "h": 32,
      "pivotX": 0,
      "pivotY": 0,
      "scaleX": 1.0,
      "scaleY": 1.0,
      "anchorToPointName": null,
      "anchorPoints": []
    },
    {
      "name": "TEXTURE_KEY_END_RIGHT",
      "x": 598,
      "y": 131,
      "w": 7,
      "h": 32,
      "pivotX": 0,
      "pivotY": 0,
      "scaleX": 1.0,
      "scaleY": 1.0,
      "anchorToPointName": null,
      "anchorPoints": []
    },
    {
      "name": "TEXTURE_KEY_MID",
      "x": 768,
      "y": 131,
      "w": 7,
      "h": 32,
      "pivotX": 0,
      "pivotY": 0,
      "scaleX": 1.0,
      "scaleY": 1.0,
      "anchorToPointName": null,
      "anchorPoints": []
    }
  ],
  "animationFramesMap": {}
}